{
  "name": "Pantera Capital Portfolio",
  "tags": {
    "pantera_capital_portfolio": {
      "name": "Pantera Capital Portfolio",
      "description": "Since 2013, Pantera has invested in digital assets and blockchain companies, providing investors with the full spectrum of exposure to the space. Pantera Capital portfolio of liquid tokens."
    }
  },
  "timestamp": "2022-12-22T00:00:00+00:00",
  "tokens": [
    {
      "chainId": 56,
      "address": "0x1d2f0da169ceb9fc7b3144628db156f3f6c60dbe",
      "symbol": "XRP",
      "name": "XRP",
      "tags": ["pantera_capital_portfolio"]
    },
    {
      "chainId": 56,
      "address": "0x0eb3a705fc54725037cc9e008bdede697f62f335",
      "symbol": "ATOM",
      "name": "ATOM",
      "tags": ["pantera_capital_portfolio"]
    },
    {
      "chainId": 1,
      "address": "0x8D983cb9388EaC77af0474fA441C4815500Cb7BB",
      "symbol": "ATOM",
      "name": "ATOM",
      "tags": ["pantera_capital_portfolio"]
    },
    {
      "chainId": 137,
      "address": "0xac51C4c48Dc3116487eD4BC16542e27B5694Da1b",
      "symbol": "ATOM",
      "name": "ATOM",
      "tags": ["pantera_capital_portfolio"]
    },
    {
      "chainId": 1,
      "address": "0xbd31ea8212119f94a611fa969881cba3ea06fa3d",
      "symbol": "LUNC",
      "name": "LUNC",
      "tags": ["pantera_capital_portfolio"]
    },
    {
      "chainId": 56,
      "address": "0x156ab3346823B651294766e23e6Cf87254d68962",
      "symbol": "LUNC",
      "name": "LUNC",
      "tags": ["pantera_capital_portfolio"]
    },
    {
      "chainId": 1,
      "address": "0x056fd409e1d7a124bd7017459dfea2f387b6d5cd",
      "symbol": "GUSD",
      "name": "GUSD",
      "tags": ["pantera_capital_portfolio"]
    },
    {
      "chainId": 56,
      "address": "0x1ba42e5193dfa8b03d15dd1b86a3113bbbef8eeb",
      "symbol": "ZEC",
      "name": "ZEC",
      "tags": ["pantera_capital_portfolio"]
    },
    {
      "chainId": 1,
      "address": "0x9f8f72aa9304c8b593d555f12ef6589cc3a579a2",
      "symbol": "MKR",
      "name": "MKR",
      "tags": ["pantera_capital_portfolio"]
    },
    {
      "chainId": 1,
      "address": "0x1A4b46696b2bB4794Eb3D4c26f1c55F9170fa4C5",
      "symbol": "BIT",
      "name": "BIT",
      "tags": ["pantera_capital_portfolio"]
    },
    {
      "chainId": 1,
      "address": "0x111111111117dc0aa78b770fa6a738034120c302",
      "symbol": "1INCH",
      "name": "1INCH",
      "tags": ["pantera_capital_portfolio"]
    },
    {
      "chainId": 56,
      "address": "0x111111111117dc0aa78b770fa6a738034120c302",
      "symbol": "1INCH",
      "name": "1INCH",
      "tags": ["pantera_capital_portfolio"]
    },
    {
      "chainId": 137,
      "address": "0x9c2c5fd7b07e95ee044ddeba0e97a665f142394f",
      "symbol": "1INCH",
      "name": "1INCH",
      "tags": ["pantera_capital_portfolio"]
    },
    {
      "chainId": 43114,
      "address": "0xd501281565bf7789224523144fe5d98e8b28f267",
      "symbol": "1INCH",
      "name": "1INCH",
      "tags": ["pantera_capital_portfolio"]
    },
    {
      "chainId": 1,
      "address": "0x0d8775f648430679a709e98d2b0cb6250d2887ef",
      "symbol": "BAT",
      "name": "BAT",
      "tags": ["pantera_capital_portfolio"]
    },
    {
      "chainId": 56,
      "address": "0x101d82428437127bf1608f699cd651e6abf9766e",
      "symbol": "BAT",
      "name": "BAT",
      "tags": ["pantera_capital_portfolio"]
    },
    {
      "chainId": 43114,
      "address": "0x98443B96EA4b0858FDF3219Cd13e98C7A4690588",
      "symbol": "BAT",
      "name": "BAT",
      "tags": ["pantera_capital_portfolio"]
    },
    {
      "chainId": 137,
      "address": "0x3cef98bb43d732e2f285ee605a8158cde967d219",
      "symbol": "BAT",
      "name": "BAT",
      "tags": ["pantera_capital_portfolio"]
    },
    {
      "chainId": 1,
      "address": "0xc00e94cb662c3520282e6f5717214004a7f26888",
      "symbol": "COMP",
      "name": "COMP",
      "tags": ["pantera_capital_portfolio"]
    },
    {
      "chainId": 137,
      "address": "0x8505b9d2254a7ae468c0e9dd10ccea3a837aef5c",
      "symbol": "COMP",
      "name": "COMP",
      "tags": ["pantera_capital_portfolio"]
    },
    {
      "chainId": 56,
      "address": "0x52CE071Bd9b1C4B00A0b92D298c512478CaD67e8",
      "symbol": "COMP",
      "name": "COMP",
      "tags": ["pantera_capital_portfolio"]
    },
    {
      "chainId": 1,
      "address": "0xba100000625a3754423978a60c9317c58a424e3D",
      "symbol": "BAL",
      "name": "BAL",
      "tags": ["pantera_capital_portfolio"]
    },
    {
      "chainId": 137,
      "address": "0x9a71012B13CA4d3D0Cdc72A177DF3ef03b0E76A3",
      "symbol": "BAL",
      "name": "BAL",
      "tags": ["pantera_capital_portfolio"]
    },
    {
      "chainId": 1,
      "address": "0x6b3595068778dd592e39a122f4f5a5cf09c90fe2",
      "symbol": "SUSHI",
      "name": "SUSHI",
      "tags": ["pantera_capital_portfolio"]
    },
    {
      "chainId": 42161,
      "address": "0xd4d42f0b6def4ce0383636770ef773390d85c61a",
      "symbol": "SUSHI",
      "name": "SUSHI",
      "tags": ["pantera_capital_portfolio"]
    },
    {
      "chainId": 250,
      "address": "0xae75A438b2E0cB8Bb01Ec1E1e376De11D44477CC",
      "symbol": "SUSHI",
      "name": "SUSHI",
      "tags": ["pantera_capital_portfolio"]
    },
    {
      "chainId": 56,
      "address": "0x947950bcc74888a40ffa2593c5798f11fc9124c4",
      "symbol": "SUSHI",
      "name": "SUSHI",
      "tags": ["pantera_capital_portfolio"]
    },
    {
      "chainId": 137,
      "address": "0x0b3f868e0be5597d5db7feb59e1cadbb0fdda50a",
      "symbol": "SUSHI",
      "name": "SUSHI",
      "tags": ["pantera_capital_portfolio"]
    },
    {
      "chainId": 43114,
      "address": "0x37b608519f91f70f2eeb0e5ed9af4061722e4f76",
      "symbol": "SUSHI",
      "name": "SUSHI",
      "tags": ["pantera_capital_portfolio"]
    },
    {
      "chainId": 1,
      "address": "0xff20817765cb7f73d4bde2e66e067e58d11095c2",
      "symbol": "AMP",
      "name": "AMP",
      "tags": ["pantera_capital_portfolio"]
    },
    {
      "chainId": 1,
      "address": "0x26B80FBfC01b71495f477d5237071242e0d959d7",
      "symbol": "ROSE",
      "name": "ROSE",
      "tags": ["pantera_capital_portfolio"]
    },
    {
      "chainId": 56,
      "address": "0x6c6D604D3f07aBE287C1A3dF0281e999A83495C0",
      "symbol": "ROSE",
      "name": "ROSE",
      "tags": ["pantera_capital_portfolio"]
    },
    {
      "chainId": 43114,
      "address": "0x12AF5C1a232675f62F405b5812A80e7a6F75D746",
      "symbol": "ROSE",
      "name": "ROSE",
      "tags": ["pantera_capital_portfolio"]
    },
    {
      "chainId": 1,
      "address": "0x8290333ceF9e6D528dD5618Fb97a76f268f3EDD4",
      "symbol": "ANKR",
      "name": "ANKR",
      "tags": ["pantera_capital_portfolio"]
    },
    {
      "chainId": 56,
      "address": "0xf307910a4c7bbc79691fd374889b36d8531b08e3",
      "symbol": "ANKR",
      "name": "ANKR",
      "tags": ["pantera_capital_portfolio"]
    },
    {
      "chainId": 1,
      "address": "0xd26114cd6EE289AccF82350c8d8487fedB8A0C07",
      "symbol": "OMG",
      "name": "OMG",
      "tags": ["pantera_capital_portfolio"]
    },
    {
      "chainId": 1,
      "address": "0xe41d2489571d322189246dafa5ebde1f4699f498",
      "symbol": "ZRX",
      "name": "ZRX",
      "tags": ["pantera_capital_portfolio"]
    },
    {
      "chainId": 43114,
      "address": "0x596fa47043f99a4e0f122243b841e55375cde0d2",
      "symbol": "ZRX",
      "name": "ZRX",
      "tags": ["pantera_capital_portfolio"]
    },
    {
      "chainId": 1,
      "address": "0x18aaa7115705e8be94bffebde57af9bfc265b998",
      "symbol": "AUDIO",
      "name": "AUDIO",
      "tags": ["pantera_capital_portfolio"]
    },
    {
      "chainId": 1,
      "address": "0xe28b3b32b6c345a34ff64674606124dd5aceca30",
      "symbol": "INJ",
      "name": "INJ",
      "tags": ["pantera_capital_portfolio"]
    },
    {
      "chainId": 56,
      "address": "0xa2b726b1145a4773f68593cf171187d8ebe4d495",
      "symbol": "INJ",
      "name": "INJ",
      "tags": ["pantera_capital_portfolio"]
    },
    {
      "chainId": 1,
      "address": "0x0b38210ea11411557c13457D4dA7dC6ea731B88a",
      "symbol": "API3",
      "name": "API3",
      "tags": ["pantera_capital_portfolio"]
    },
    {
      "chainId": 1,
      "address": "0xdeFA4e8a7bcBA345F687a2f1456F5Edd9CE97202",
      "symbol": "KNC",
      "name": "KNC",
      "tags": ["pantera_capital_portfolio"]
    },
    {
      "chainId": 137,
      "address": "0x1c954e8fe737f99f68fa1ccda3e51ebdb291948c",
      "symbol": "KNC",
      "name": "KNC",
      "tags": ["pantera_capital_portfolio"]
    },
    {
      "chainId": 56,
      "address": "0xfe56d5892bdffc7bf58f2e84be1b2c32d21c308b",
      "symbol": "KNC",
      "name": "KNC",
      "tags": ["pantera_capital_portfolio"]
    },
    {
      "chainId": 1,
      "address": "0x41e5560054824ea6b0732e656e3ad64e20e94e45",
      "symbol": "CVC",
      "name": "CVC",
      "tags": ["pantera_capital_portfolio"]
    },
    {
      "chainId": 1,
      "address": "0x419d0d8bdd9af5e606ae2232ed285aff190e711b",
      "symbol": "FUN",
      "name": "FUN",
      "tags": ["pantera_capital_portfolio"]
    },
    {
      "chainId": 1,
      "address": "0x4f9254c83eb525f9fcf346490bbb3ed28a81c667",
      "symbol": "CELR",
      "name": "CELR",
      "tags": ["pantera_capital_portfolio"]
    },
    {
      "chainId": 56,
      "address": "0x1f9f6a696c6fd109cd3956f45dc709d2b3902163",
      "symbol": "CELR",
      "name": "CELR",
      "tags": ["pantera_capital_portfolio"]
    },
    {
      "chainId": 1,
      "address": "0x6DEA81C8171D0bA574754EF6F8b412F2Ed88c54D",
      "symbol": "LQTY",
      "name": "LQTY",
      "tags": ["pantera_capital_portfolio"]
    },
    {
      "chainId": 1,
      "address": "0x8207c1ffc5b6804f6024322ccf34f29c3541ae26",
      "symbol": "OGN",
      "name": "OGN",
      "tags": ["pantera_capital_portfolio"]
    },
    {
      "chainId": 1,
      "address": "0xd46ba6d942050d489dbd938a2c909a5d5039a161",
      "symbol": "AMPL",
      "name": "AMPL",
      "tags": ["pantera_capital_portfolio"]
    },
    {
      "chainId": 1,
      "address": "0x43dfc4159d86f3a37a5a4b3d4580b888ad7d4ddd",
      "symbol": "DODO",
      "name": "DODO",
      "tags": ["pantera_capital_portfolio"]
    },
    {
      "chainId": 56,
      "address": "0x67ee3cb086f8a16f34bee3ca72fad36f7db929e2",
      "symbol": "DODO",
      "name": "DODO",
      "tags": ["pantera_capital_portfolio"]
    },
    {
      "chainId": 137,
      "address": "0xe4bf2864ebec7b7fdf6eeca9bacae7cdfdaffe78",
      "symbol": "DODO",
      "name": "DODO",
      "tags": ["pantera_capital_portfolio"]
    },
    {
      "chainId": 1,
      "address": "0x221657776846890989a759BA2973e427DfF5C9bB",
      "symbol": "REP",
      "name": "REP",
      "tags": ["pantera_capital_portfolio"]
    },
    {
      "chainId": 1,
      "address": "0x57b946008913b82e4df85f501cbaed910e58d26c",
      "symbol": "POND",
      "name": "POND",
      "tags": ["pantera_capital_portfolio"]
    },
    {
      "chainId": 1,
      "address": "0x1e053d89e08c24aa2ce5c5b4206744dc2d7bd8f5",
      "symbol": "TT",
      "name": "TT",
      "tags": ["pantera_capital_portfolio"]
    },
    {
      "chainId": 1,
      "address": "0xa9b1eb5908cfc3cdf91f9b8b3a74108598009096",
      "symbol": "AUCTION",
      "name": "AUCTION",
      "tags": ["pantera_capital_portfolio"]
    },
    {
      "chainId": 1,
      "address": "0xcb84d72e61e383767c4dfeb2d8ff7f4fb89abc6e",
      "symbol": "VEGA",
      "name": "VEGA",
      "tags": ["pantera_capital_portfolio"]
    },
    {
      "chainId": 1,
      "address": "0xaaaaaa20d9e0e2461697782ef11675f668207961",
      "symbol": "AURORA",
      "name": "AURORA",
      "tags": ["pantera_capital_portfolio"]
    },
    {
      "chainId": 1,
      "address": "0xaaef88cea01475125522e117bfe45cf32044e238",
      "symbol": "GF",
      "name": "GF",
      "tags": ["pantera_capital_portfolio"]
    },
    {
      "chainId": 1,
      "address": "0x09a3EcAFa817268f77BE1283176B946C4ff2E608",
      "symbol": "MIR",
      "name": "MIR",
      "tags": ["pantera_capital_portfolio"]
    },
    {
      "chainId": 1,
      "address": "0xc770eefad204b5180df6a14ee197d99d808ee52d",
      "symbol": "FOX",
      "name": "FOX",
      "tags": ["pantera_capital_portfolio"]
    },
    {
      "chainId": 137,
      "address": "0x65A05DB8322701724c197AF82C9CaE41195B0aA8",
      "symbol": "FOX",
      "name": "FOX",
      "tags": ["pantera_capital_portfolio"]
    },
    {
      "chainId": 1,
      "address": "0x799ebfabe77a6e34311eeee9825190b9ece32824",
      "symbol": "BTRST",
      "name": "BTRST",
      "tags": ["pantera_capital_portfolio"]
    },
    {
      "chainId": 1,
      "address": "0x6f40d4A6237C257fff2dB00FA0510DeEECd303eb",
      "symbol": "INST",
      "name": "INST",
      "tags": ["pantera_capital_portfolio"]
    },
    {
      "chainId": 1,
      "address": "0xc5bbae50781be1669306b9e001eff57a2957b09d",
      "symbol": "GTO",
      "name": "GTO",
      "tags": ["pantera_capital_portfolio"]
    },
    {
      "chainId": 1,
      "address": "0xC229c69eB3BB51828D0cAA3509A05a51083898dd",
      "symbol": "PTU",
      "name": "PTU",
      "tags": ["pantera_capital_portfolio"]
    },
    {
      "chainId": 1,
      "address": "0x6243d8cea23066d098a15582d81a598b4e8391f4",
      "symbol": "FLX",
      "name": "FLX",
      "tags": ["pantera_capital_portfolio"]
    },
    {
      "chainId": 1,
      "address": "0x8dBF9A4c99580fC7Fd4024ee08f3994420035727",
      "symbol": "ECO",
      "name": "ECO",
      "tags": ["pantera_capital_portfolio"]
    },
    {
      "chainId": 1,
      "address": "0xcfeaead4947f0705a14ec42ac3d44129e1ef3ed5",
      "symbol": "NOTE",
      "name": "NOTE",
      "tags": ["pantera_capital_portfolio"]
    },
    {
      "chainId": 56,
      "address": "0xc2098a8938119A52B1F7661893c0153A6CB116d5",
      "symbol": "RPG",
      "name": "RPG",
      "tags": ["pantera_capital_portfolio"]
    },
    {
      "chainId": 1,
      "address": "0x0E5C8C387C5EBa2eCbc137aD012aeD5Fe729e251",
      "symbol": "RPG",
      "name": "RPG",
      "tags": ["pantera_capital_portfolio"]
    },
    {
      "chainId": 1,
      "address": "0x30D20208d987713f46DFD34EF128Bb16C404D10f",
      "symbol": "SD",
      "name": "SD",
      "tags": ["pantera_capital_portfolio"]
    },
    {
      "chainId": 1,
      "address": "0x188e817b02e635d482ae4d81e25dda98a97c4a42",
      "symbol": "LITH",
      "name": "LITH",
      "tags": ["pantera_capital_portfolio"]
    },
    {
      "chainId": 56,
      "address": "0x9df465460938f9EBDF51C38CC87D72184471F8F0",
      "symbol": "GENE",
      "name": "GENE",
      "tags": ["pantera_capital_portfolio"]
    },
    {
      "chainId": 1,
      "address": "0x60be1e1fe41c1370adaf5d8e66f07cf1c2df2268",
      "symbol": "PERC",
      "name": "PERC",
      "tags": ["pantera_capital_portfolio"]
    },
    {
      "chainId": 1,
      "address": "0x8db253a1943dddf1af9bcf8706ac9a0ce939d922",
      "symbol": "UNB",
      "name": "UNB",
      "tags": ["pantera_capital_portfolio"]
    },
    {
      "chainId": 56,
      "address": "0x301af3eff0c904dc5ddd06faa808f653474f7fcc",
      "symbol": "UNB",
      "name": "UNB",
      "tags": ["pantera_capital_portfolio"]
    },
    {
      "chainId": 137,
      "address": "0xD81F558b71A5323e433729009D55159955F8A7f9",
      "symbol": "UNB",
      "name": "UNB",
      "tags": ["pantera_capital_portfolio"]
    },
    {
      "chainId": 1,
      "address": "0xf0ee6b27b759c9893ce4f094b49ad28fd15a23e4",
      "symbol": "ENG",
      "name": "ENG",
      "tags": ["pantera_capital_portfolio"]
    },
    {
      "chainId": 1,
      "address": "0xC57d533c50bC22247d49a368880fb49a1caA39F7",
      "symbol": "PTF",
      "name": "PTF",
      "tags": ["pantera_capital_portfolio"]
    },
    {
      "chainId": 1,
      "address": "0x5eeaa2dcb23056f4e8654a349e57ebe5e76b5e6e",
      "symbol": "VPP",
      "name": "VPP",
      "tags": ["pantera_capital_portfolio"]
    },
    {
      "chainId": 1,
      "address": "0xc7bba5b765581efb2cdd2679db5bea9ee79b201f",
      "symbol": "GEM",
      "name": "GEM",
      "tags": ["pantera_capital_portfolio"]
    }
  ],
  "version": {
    "major": 1,
    "minor": 0,
    "patch": 0
  }
}
